LICENSE.txt
MANIFEST.in
Makefile
README.rst
setup.cfg
setup.py
docs/Makefile
docs/conf.py
docs/index.rst
docs/make.bat
docs/objects.rst
thobject/__init__.py
thobject/_base.py
thobject/_cache.py
thobject/_props.py
thobject/version.py
thobject.egg-info/PKG-INFO
thobject.egg-info/SOURCES.txt
thobject.egg-info/dependency_links.txt
thobject.egg-info/not-zip-safe
thobject.egg-info/requires.txt
thobject.egg-info/top_level.txt