Metadata-Version: 1.1
Name: thobject
Version: 0.1
Summary: simple database-like objects
Home-page: https://thobject.touhey.pro/
Author: Thomas Touhey
Author-email: thomas@touhey.fr
License: MIT
Keywords: object
Platform: UNKNOWN
Classifier: Development Status :: 2 - Pre-Alpha
Classifier: License :: OSI Approved :: MIT License
Classifier: Operating System :: OS Independent
Classifier: Programming Language :: Python :: 3
